odoo8_addon_l10n_it_abicab-8.0.1.1.0-nspkg.pth
odoo_addons/l10n_it_abicab/README.rst
odoo_addons/l10n_it_abicab/__init__.py
odoo_addons/l10n_it_abicab/__openerp__.py
odoo_addons/l10n_it_abicab/abicab.py
odoo_addons/l10n_it_abicab/abicab_view.xml
odoo_addons/l10n_it_abicab/i18n/it.po
odoo_addons/l10n_it_abicab/i18n/l10n_it_abicab.pot
odoo_addons/l10n_it_abicab/i18n/sl.po
odoo_addons/l10n_it_abicab/static/description/icon.png
odoo_addons/l10n_it_abicab/test/abicab.yml
odoo8_addon_l10n_it_abicab-8.0.1.1.0.dist-info/METADATA
odoo8_addon_l10n_it_abicab-8.0.1.1.0.dist-info/WHEEL
odoo8_addon_l10n_it_abicab-8.0.1.1.0.dist-info/namespace_packages.txt
odoo8_addon_l10n_it_abicab-8.0.1.1.0.dist-info/top_level.txt
odoo8_addon_l10n_it_abicab-8.0.1.1.0.dist-info/RECORD
