Metadata-Version: 2.1
Name: odoo8-addon-l10n-it-abicab
Version: 8.0.1.1.0
Summary: Base Bank ABI/CAB codes
Home-page: http://www.odoo-italia.org/
Author: OpenERP Italian Community,Odoo Community Association (OCA)
Author-email: support@odoo-community.org
License: AGPL-3
Platform: UNKNOWN
Classifier: Programming Language :: Python
Classifier: Framework :: Odoo
Classifier: License :: OSI Approved :: GNU Affero General Public License v3
Requires-Python: ~=2.7
Requires-Dist: odoo (<9.0a,>=8.0a)
